salvitobot/salvito_email.py
salvitobot/config.py
salvitobot/utils.py
salvitobot/__init__.py
salvitobot/salvito_twitter.py
salvitobot/exceptions.py
salvitobot/api.py
salvitobot/writer.py
salvitobot/salvito_wordpress.py
salvitobot-0.4.1.dist-info/top_level.txt
salvitobot-0.4.1.dist-info/RECORD
salvitobot-0.4.1.dist-info/WHEEL
salvitobot-0.4.1.dist-info/metadata.json
salvitobot-0.4.1.dist-info/METADATA
salvitobot-0.4.1.dist-info/DESCRIPTION.rst
