Metadata-Version: 2.0
Name: salvitobot
Version: 0.4.1
Summary: avisa sismos
Home-page: https://github.com/aniversarioperu/salvitobot
Author: AniversarioPeru
Author-email: aniversarioperu1@gmail.com
License: UNKNOWN
Platform: UNKNOWN
Classifier: Development Status :: 2 - Pre-Alpha
Classifier: Programming Language :: Python
Classifier: Programming Language :: Python :: 3.4
Requires-Dist: dataset
Requires-Dist: python-wordpress-xmlrpc
Requires-Dist: requests
Requires-Dist: feedparser
Requires-Dist: requests-oauthlib
Requires-Dist: pytz
Requires-Dist: arrow
Requires-Dist: slugify
